{
	"storyName": "a New Connection.",
	"difficulties": "Hard",
	"hideFreeplay": false,
	"weekBackground": "white-space",
	"weekBefore": "",
	"startUnlocked": true,
	"hideStoryMode": false,
	"weekCharacters": [
		"",
		"",
		""
	],
	"songs": [
		[
			"Purple Red",
			"nxxty",
			[
				226,
				20,
				155
			]
		],
		[
			"Protocol",
			"nxxty",
			[
				226,
				20,
				155
			]
		],
		[
			"Citriky",
			"nxxty",
			[
				226,
				20,
				155
			]
		],
		[
			"Seamless",
			"nxxty",
			[
				226,
				20,
				155
			]
		],
		[
			"Wannacry",
			"nxxty",
			[
				226,
				20,
				155
			]
		]
	],
	"weekName": "Connected",
	"hiddenUntilUnlocked": false
}